environment_helpers/__init__.py
environment_helpers/command_validation.py
environment_helpers/config_reader.py
environment_helpers/query_utilities.py
environment_helpers/tag_functions.py
bpp_env_helpers-0.0.9.dist-info/LICENSE
bpp_env_helpers-0.0.9.dist-info/METADATA
bpp_env_helpers-0.0.9.dist-info/WHEEL
bpp_env_helpers-0.0.9.dist-info/top_level.txt
bpp_env_helpers-0.0.9.dist-info/RECORD
