Metadata-Version: 2.1
Name: bpp-env-helpers
Version: 0.0.9
Summary: misc helpers for bpp behave tests
Home-page: https://gitlab.com/blueprintprep/bpp-qa/utilities/environment-helpers
Author: matthew bahloul
Author-email: matthew.bahloul@blueprintprep.com
Project-URL: Bug Tracker, https://gitlab.com/blueprintprep/bpp-qa/utilities/environment-helpers/-/issues
Classifier: Programming Language :: Python :: 3
Classifier: License :: OSI Approved :: MIT License
Classifier: Operating System :: OS Independent
Requires-Python: >=3.6
License-File: LICENSE
